setup.cfg
setup.py
evalnumstr/__init__.py
evalnumstr.egg-info/PKG-INFO
evalnumstr.egg-info/SOURCES.txt
evalnumstr.egg-info/dependency_links.txt
evalnumstr.egg-info/not-zip-safe
evalnumstr.egg-info/top_level.txt