Metadata-Version: 1.0
Name: evalnumstr
Version: 0.0.10
Summary: Evaluate number string
Home-page: UNKNOWN
Author: FotonPC
Author-email: foton-pc@inbox.ru
License: UNKNOWN
Platform: UNKNOWN
